spleeter/__init__.py
spleeter/__main__.py
spleeter/audio/__init__.py
spleeter/audio/adapter.py
spleeter/audio/convertor.py
spleeter/audio/ffmpeg.py
spleeter/audio/spectrogram.py
spleeter/dataset.py
spleeter/model/__init__.py
spleeter/model/functions/__init__.py
spleeter/model/functions/blstm.py
spleeter/model/functions/unet.py
spleeter/model/provider/__init__.py
spleeter/model/provider/github.py
spleeter/options.py
spleeter/py.typed
spleeter/resources/2stems-16kHz.json
spleeter/resources/2stems.json
spleeter/resources/4stems-16kHz.json
spleeter/resources/4stems.json
spleeter/resources/5stems-16kHz.json
spleeter/resources/5stems.json
spleeter/resources/__init__.py
spleeter/resources/musdb.json
spleeter/separator.py
spleeter/types.py
spleeter/utils/__init__.py
spleeter/utils/configuration.py
spleeter/utils/logging.py
spleeter/utils/tensor.py
spleeter-2.4.2.dist-info/LICENSE
spleeter-2.4.2.dist-info/METADATA
spleeter-2.4.2.dist-info/WHEEL
spleeter-2.4.2.dist-info/entry_points.txt
spleeter-2.4.2.dist-info/RECORD
