Metadata-Version: 2.3
Name: spleeter
Version: 2.4.2
Summary: The Deezer source separation library with pretrained models based on tensorflow.
License: MIT
Author: Deezer Research
Author-email: spleeter@deezer.com
Requires-Python: >=3.8,<3.12
Classifier: Environment :: Console
Classifier: Environment :: MacOS X
Classifier: Intended Audience :: Developers
Classifier: Intended Audience :: Information Technology
Classifier: Intended Audience :: Science/Research
Classifier: License :: OSI Approved :: MIT License
Classifier: Natural Language :: English
Classifier: Operating System :: MacOS
Classifier: Operating System :: Microsoft :: Windows
Classifier: Operating System :: POSIX :: Linux
Classifier: Operating System :: Unix
Classifier: Programming Language :: Python
Classifier: Programming Language :: Python :: 3
Classifier: Programming Language :: Python :: 3.8
Classifier: Programming Language :: Python :: 3.9
Classifier: Programming Language :: Python :: 3.10
Classifier: Programming Language :: Python :: 3.11
Classifier: Programming Language :: Python :: 3 :: Only
Classifier: Programming Language :: Python :: Implementation :: CPython
Classifier: Topic :: Artistic Software
Classifier: Topic :: Multimedia
Classifier: Topic :: Multimedia :: Sound/Audio
Classifier: Topic :: Multimedia :: Sound/Audio :: Analysis
Classifier: Topic :: Multimedia :: Sound/Audio :: Conversion
Classifier: Topic :: Multimedia :: Sound/Audio :: Sound Synthesis
Classifier: Topic :: Scientific/Engineering
Classifier: Topic :: Scientific/Engineering :: Artificial Intelligence
Classifier: Topic :: Scientific/Engineering :: Information Analysis
Classifier: Topic :: Software Development
Classifier: Topic :: Software Development :: Libraries
Classifier: Topic :: Software Development :: Libraries :: Python Modules
Classifier: Topic :: Utilities
Provides-Extra: evaluation
Requires-Dist: ffmpeg-python (>=0.2.0,<0.3.0)
Requires-Dist: httpx[http2] (>=0.19.0,<0.20.0)
Requires-Dist: musdb (>=0.4.0,<0.5.0) ; extra == "evaluation"
Requires-Dist: museval (>=0.4.0,<0.5.0) ; extra == "evaluation"
Requires-Dist: norbert (>=0.2.1,<0.3.0)
Requires-Dist: numpy (<2.0.0)
Requires-Dist: pandas (>=1.3.0,<2.0.0)
Requires-Dist: tensorflow (==2.12.1)
Requires-Dist: tensorflow-io-gcs-filesystem (==0.32.0)
Requires-Dist: typer (>=0.3.2,<0.4.0)
Project-URL: Homepage, https://github.com/deezer/spleeter
Project-URL: Repository, https://github.com/deezer/spleeter
